python_veracity-0.0.10.data/scripts/vv-builder-script.py
python_veracity-0.0.10.data/scripts/vv-builder.exe
python_veracity-0.0.10.data/scripts/vv-builder.exe.manifest
python_veracity-0.0.10.data/scripts/vv-poller-script.py
python_veracity-0.0.10.data/scripts/vv-poller.exe
python_veracity-0.0.10.data/scripts/vv-poller.exe.manifest
python_veracity-0.0.10.data/scripts/vv-tracking-script.py
python_veracity-0.0.10.data/scripts/vv-tracking.exe
python_veracity-0.0.10.data/scripts/vv-tracking.exe.manifest
python_veracity-0.0.10.dist-info/DESCRIPTION.rst
python_veracity-0.0.10.dist-info/entry_points.txt
python_veracity-0.0.10.dist-info/METADATA
python_veracity-0.0.10.dist-info/pydist.json
python_veracity-0.0.10.dist-info/RECORD
python_veracity-0.0.10.dist-info/top_level.txt
python_veracity-0.0.10.dist-info/WHEEL
veracity/builder.py
veracity/common.py
veracity/objects.py
veracity/poller.py
veracity/settings.py
veracity/tracking.py
veracity/vscript.py
veracity/vv.py
veracity/__init__.py
veracity/files/init_builds.js
veracity/files/report_build.js
veracity/files/report_build_lib.js
veracity/test/test_builder.py
veracity/test/test_common.py
veracity/test/test_objects.py
veracity/test/test_poller.py
veracity/test/test_tracking.py
veracity/test/test_vscript.py
veracity/test/test_vv.py
veracity/test/__init__.py
veracity/test/files/builder.cfg
veracity/test/files/poller.cfg
veracity/test/files/setup.cfg
