Metadata-Version: 2.0
Name: python-veracity
Version: 0.0.10
Summary: Python wrapper for Veracity's command-line interface.
Home-page: http://pypi.python.org/pypi/python-veracity
Author: Jace Browning
Author-email: jacebrowning@gmail.com
License: LICENSE.txt
Platform: UNKNOWN
Requires-Dist: pbs (>=0.110)
Requires-Dist: virtualenv (>=1.9.1)
